<?xml version="1.0" encoding="utf-8"?>
<ModMetaData>
  <name>Minerals Framework</name>
  <author>Zachary S. L. Foster</author>
	<packageId>zacharyfoster.mineralsframework</packageId>
  <description>An overhaul of anything mineable and the foundation for the "Minerals" collection of mods. Includes:

- Realistic organic mineral appearances with varied sizes and textures
- Dynamic mineral growth/shrinking based on environmental conditions
- Mining yields affected by miner skill and mineral size
- Gradual resource drops during mining instead of instant drops
- Snow accumulation effects on textures
- Customizable mining products with probabilities/quantities

Compatible with most mods. Part of the Minerals collection:
- Minerals Rock, Minerals Sparkle, Minerals Craft
- Minerals Exotic, Minerals Frozen, and more</description>
  <url>https://github.com/zachary-foster/MineralsFramework</url>
  <supportedVersions>
    <li>1.6</li>
  </supportedVersions>
  <modDependencies>
    <li>
      <packageId>brrainz.harmony</packageId>
      <displayName>Harmony</displayName>
      <steamWorkshopUrl>steam://url/CommunityFilePage/2009463077</steamWorkshopUrl>
    </li>
  </modDependencies>
	<loadAfter>
		<li>sarg.alphabiomes</li>
	</loadAfter>
</ModMetaData>
